mu0_reg12.v
// MU0 12 bit register design - behavioural style
// S Tatu (based on a design by Jeff Pepper)
// Date 12/12/2020
// 

// Do not touch the following line it is required for simulation 
`timescale 1ns/100ps

// for simulation purposes, do not delete
`default_nettype none

// module header

module mu0_reg12(input  wire        Clk, 
	             input  wire        Reset,     
			     input  wire        En, 
			     input  wire [11:0] D, 
			     output reg  [11:0] Q);

// behavioural code - clock driven

always @(posedge Clk)
    if (Reset)
        Q <= 12'h000;
    else if (En)
        Q <= D;

endmodule 

// for simulation purposes, do not delete
`default_nettype wire

mu0_reg12_tb.v
// MU0 12 bit register testbench
// S Tatu (based on a design by Jeff Pepper)
// Date 13/12/2020
// 

// Do not touch the following line it is required for simulation 
`timescale 1ns/100ps 

// module header

module mu0_reg12_tb();

// Internal connections
reg Clk;
reg Reset;
reg En;
reg [11:0] D;
wire [11:0] Q;

mu0_reg12 dut (Clk, Reset, En, D, Q);
// Instantiate mu0_reg12 as dut (device under test)
// Uses explicit dot pins - safer than position substitution




// Set up the clock

initial Clk= 0;
always // always do the following
    begin
    #50 // wait half a clock period
    Clk = ~Clk; // invert the clock
    end

// Test vectors
initial
begin
En = 1'b0; Reset = 1'b0; D=12'h101;
#100 En = 1'b1;
#100 D = 12'h111;
#100 D = 12'h000; En = 1'b0;
#100 D = 12'h100;
#100 En = 1'b1;
#100 D = 12'h110;
#100 D = 12'h011; Reset = 1'b1;
#100 D = 12'h001; Reset = 1'b0;

  #100 $finish;      // end the simulation
end
 
// Save results as VCD file 
// Do not change
initial
 begin
  $dumpfile("mu0_reg12_tb_results.vcd");  // Save simulation waveforms in this file
  $dumpvars; // Capture all simulation waveforms
 end

endmodule

mu0_reg12_tb_results.vcd
$date
	Tue Dec 15 19:19:35 2020
$end
$version
	Icarus Verilog
$end
$timescale
	100ps
$end
$scope module mu0_reg12_tb $end
$var wire 12 ! Q [11:0] $end
$var reg 1 " Clk $end
$var reg 12 # D [11:0] $end
$var reg 1 $ En $end
$var reg 1 % Reset $end
$scope module dut $end
$var wire 1 " Clk $end
$var wire 12 & D [11:0] $end
$var wire 1 $ En $end
$var wire 1 % Reset $end
$var reg 12 ' Q [11:0] $end
$upscope $end
$upscope $end
$enddefinitions $end
#0
$dumpvars
bx '
b100000001 &
0%
0$
b100000001 #
0"
bx !
$end
#500
1"
#1000
0"
1$
#1500
b100000001 !
b100000001 '
1"
#2000
0"
b100010001 #
b100010001 &
#2500
b100010001 !
b100010001 '
1"
#3000
0"
0$
b0 #
b0 &
#3500
1"
#4000
0"
b100000000 #
b100000000 &
#4500
1"
#5000
0"
1$
#5500
b100000000 !
b100000000 '
1"
#6000
0"
b100010000 #
b100010000 &
#6500
b100010000 !
b100010000 '
1"
#7000
0"
1%
b10001 #
b10001 &
#7500
b0 !
b0 '
1"
#8000
0"
0%
b1 #
b1 &
#8500
b1 !
b1 '
1"
