mu0_reg16.v
// MU0 16 bit register design - behavioural style
// S Tatu (based on a design by Jeff Pepper)
// Date 12/12/2020
// 

// Do not touch the following line it is required for simulation 
`timescale 1ns/100ps

// for simulation purposes, do not delete
`default_nettype none

// module header

module mu0_reg16(input  wire        Clk, 
	             input  wire        Reset,     
			     input  wire        En, 
			     input  wire [15:0] D, 
			     output reg  [15:0] Q);

// behavioural code - clock driven


always @(posedge Clk)
    if (Reset)
        Q <= 16'h0000;
    else if (En)
        Q <= D;


endmodule 

// for simulation purposes, do not delete
`default_nettype wire

mu0_reg16_tb.v
// MU0 16 bit register testbench
// S Tatu (based on a design by Jeff Pepper)
// Date 12/12/2020
// 

// Do not touch the following line it is required for simulation 
`timescale 1ns/100ps 

// module header

module mu0_reg16_tb();

// Internal connections

reg Clk;
reg Reset;
reg En;
reg [15:0] D;
wire [15:0] Q;


mu0_reg16 dut (Clk, Reset, En, D, Q);
// Instantiate mu0_reg16 as dut (device under test)
// Uses explicit dot pins - safer than position substitution




// Set up the clock

initial Clk= 0;
always // always do the following
    begin
    #50 // wait half a clock period
    Clk = ~Clk; // invert the clock
    end

// Test vectors
initial
 begin
En = 1'b0; Reset = 1'b0; D=16'h0000;
#100 En = 1'b1;
#100 D = 16'h1111;
#100 D = 16'h1001; En = 1'b0;
#100 D = 16'h1100;
#100 En = 1'b1;
#100 D = 16'h1000;
#100 D = 16'h0001; Reset = 1'b1;
#100 D = 16'h1010; Reset = 1'b0;
  
   
  #100 $finish;      // exit the simulation
 end
 
// Save results as VCD file 
// Do not change
initial
 begin
  $dumpfile("mu0_reg16_tb_results.vcd");  // Save simulation waveforms in this file
  $dumpvars; // Capture all simulation waveforms
 end

endmodule

mu0_reg16_tb_results.vcd
$date
	Tue Dec 15 19:29:45 2020
$end
$version
	Icarus Verilog
$end
$timescale
	100ps
$end
$scope module mu0_reg16_tb $end
$var wire 16 ! Q [15:0] $end
$var reg 1 " Clk $end
$var reg 16 # D [15:0] $end
$var reg 1 $ En $end
$var reg 1 % Reset $end
$scope module dut $end
$var wire 1 " Clk $end
$var wire 16 & D [15:0] $end
$var wire 1 $ En $end
$var wire 1 % Reset $end
$var reg 16 ' Q [15:0] $end
$upscope $end
$upscope $end
$enddefinitions $end
#0
$dumpvars
bx '
b0 &
0%
0$
b0 #
0"
bx !
$end
#500
1"
#1000
0"
1$
#1500
b0 !
b0 '
1"
#2000
0"
b1000100010001 #
b1000100010001 &
#2500
b1000100010001 !
b1000100010001 '
1"
#3000
0"
0$
b1000000000001 #
b1000000000001 &
#3500
1"
#4000
0"
b1000100000000 #
b1000100000000 &
#4500
1"
#5000
0"
1$
#5500
b1000100000000 !
b1000100000000 '
1"
#6000
0"
b1000000000000 #
b1000000000000 &
#6500
b1000000000000 !
b1000000000000 '
1"
#7000
0"
1%
b1 #
b1 &
#7500
b0 !
b0 '
1"
#8000
0"
0%
b1000000010000 #
b1000000010000 &
#8500
b1000000010000 !
b1000000010000 '
1"
